textalytics_client/text_analysis.py
textalytics_python_client-0.1.1.dist-info/entry_points.txt
textalytics_python_client-0.1.1.dist-info/WHEEL
textalytics_python_client-0.1.1.dist-info/METADATA
textalytics_python_client-0.1.1.dist-info/RECORD
