Metadata-Version: 2.1
Name: textalytics-python-client
Version: 0.1.1
Summary: python client to interface with textalytics hosted nlp service
License: MIT
Author: Manoj Bharadwaj
Author-email: manoj@cloudcosmos.tech
Requires-Python: >=3.8,<4.0
Classifier: License :: OSI Approved :: MIT License
Classifier: Programming Language :: Python :: 3
Classifier: Programming Language :: Python :: 3.8
Classifier: Programming Language :: Python :: 3.9
Requires-Dist: requests (>=2.26.0,<3.0.0)
Requires-Dist: textalytics-core (>=0.1.2,<0.2.0)
